testing/__init__.py
testing/testing.py
testing123123-1246853394.dist-info/METADATA
testing123123-1246853394.dist-info/WHEEL
testing123123-1246853394.dist-info/top_level.txt
testing123123-1246853394.dist-info/RECORD
