Metadata-Version: 2.1
Name: testing123123
Version: 1246853394
Summary: Utility code 
Home-page: https://gitlab.com/Rahultrel/testing
Author: Rahul Kumar
Author-email: rahul@trell.in
License: UNKNOWN
Platform: UNKNOWN
Classifier: Development Status :: 2 - Pre-Alpha
Classifier: Programming Language :: Python :: 3.6
Classifier: Topic :: Scientific/Engineering :: Artificial Intelligence
Requires-Python: >=3.6.9
Requires-Dist: requests
